stscraper/__init__.py
stscraper/base.py
stscraper/github.py
strudel.scraper-1.4.0.dist-info/LICENSE
strudel.scraper-1.4.0.dist-info/METADATA
strudel.scraper-1.4.0.dist-info/WHEEL
strudel.scraper-1.4.0.dist-info/entry_points.txt
strudel.scraper-1.4.0.dist-info/top_level.txt
strudel.scraper-1.4.0.dist-info/RECORD
